pyrndr/__init__.py
pyrndr/pyrndr.py
pyrndr-0.1.2.dist-info/LICENSE.md
pyrndr-0.1.2.dist-info/METADATA
pyrndr-0.1.2.dist-info/WHEEL
pyrndr-0.1.2.dist-info/top_level.txt
pyrndr-0.1.2.dist-info/RECORD
