Metadata-Version: 2.1
Name: pyrndr
Version: 0.1.2
Summary: Platform-agnostic Python mesh renderer with minimum features
Author: Yuki Kawana
License: MIT
Project-URL: Homepage, https://github.com/ykkawana/pyrndr
License-File: LICENSE.md
Requires-Dist: trimesh
Requires-Dist: scipy
Requires-Dist: Rtree
Requires-Dist: embreex; platform_machine == "x86_64"
Provides-Extra: dev
Requires-Dist: pre-commit; extra == "dev"
Requires-Dist: build; extra == "dev"
Requires-Dist: twin; extra == "dev"
Provides-Extra: vis
Requires-Dist: matplotlib; extra == "vis"
Requires-Dist: ipykernel; extra == "vis"
